mongopersistence/__init__.py
mongopersistence/persistence.py
mongopersistence-0.3.1.dist-info/LICENSE
mongopersistence-0.3.1.dist-info/METADATA
mongopersistence-0.3.1.dist-info/WHEEL
mongopersistence-0.3.1.dist-info/RECORD
