Metadata-Version: 2.1
Name: mongopersistence
Version: 0.3.1
Summary: Package to add persistence to your telegram bot using pymongo
License: MIT
Author: LucaSforza
Author-email: lucasforza1234@icloud.com
Requires-Python: >=3.10,<4.0
Classifier: License :: OSI Approved :: MIT License
Classifier: Programming Language :: Python :: 3
Classifier: Programming Language :: Python :: 3.10
Classifier: Programming Language :: Python :: 3.11
Requires-Dist: motor (>=3.1.2,<4.0.0)
Requires-Dist: python-telegram-bot (>=20.1)
